mdf_toolbox/__init__.py
mdf_toolbox/auth.py
mdf_toolbox/filesystem.py
mdf_toolbox/globus_transfer.py
mdf_toolbox/json_dict.py
mdf_toolbox/jsonschema.py
mdf_toolbox/version.py
mdf_toolbox/globus_search/__init__.py
mdf_toolbox/globus_search/search_helper.py
mdf_toolbox/globus_search/sub_helpers.py
mdf_toolbox/globus_search/utils.py
mdf_toolbox-0.7.1.dist-info/LICENSE
mdf_toolbox-0.7.1.dist-info/METADATA
mdf_toolbox-0.7.1.dist-info/NOTICE
mdf_toolbox-0.7.1.dist-info/WHEEL
mdf_toolbox-0.7.1.dist-info/top_level.txt
mdf_toolbox-0.7.1.dist-info/RECORD
