Metadata-Version: 2.1
Name: mdf_toolbox
Version: 0.7.1
Summary: Materials Data Facility Python utilities
Home-page: https://github.com/materials-data-facility/toolbox
License: Apache License, Version 2.0
Keywords: MDF,Materials Data Facility,materials science,utility
Classifier: Development Status :: 3 - Alpha
Classifier: License :: OSI Approved :: Apache Software License
Classifier: Natural Language :: English
Classifier: Operating System :: OS Independent
Classifier: Programming Language :: Python :: 3
Requires-Python: >=3.6
License-File: LICENSE
License-File: NOTICE
Requires-Dist: fair-research-login >=0.2.4
Requires-Dist: globus-sdk >=3.1.0
Requires-Dist: requests >=2.26.0
Requires-Dist: jsonschema >=4.3.0
